Enkianthus_tts/__init__.py
Enkianthus_tts/enk.py
Enkianthus_tts-0.1.8.dist-info/LICENSE
Enkianthus_tts-0.1.8.dist-info/METADATA
Enkianthus_tts-0.1.8.dist-info/WHEEL
Enkianthus_tts-0.1.8.dist-info/top_level.txt
Enkianthus_tts-0.1.8.dist-info/RECORD
