Metadata-Version: 2.1
Name: Enkianthus_tts
Version: 0.1.8
Summary: modelscopeTTS Unofficial api,see https://github.com/avilliai/modelscopeTTS for more information
Home-page: https://github.com/avilliai/modelscopeTTS
Author: avillia
Author-email: larea06@gmail.com
License-File: LICENSE
Requires-Dist: httpx
Requires-Dist: websockets
Requires-Dist: requests
